DataSocket/DataSocket.py
DataSocket/TCPDataSocket.py
DataSocket/UDPDataSocket.py
DataSocket/__init__.py
DataSocket/Matlab/TCPReceiveSocket.m
DataSocket/Matlab/TCPSendSocket.m
PyDataSocket-0.0.52.dist-info/LICENSE.txt
PyDataSocket-0.0.52.dist-info/METADATA
PyDataSocket-0.0.52.dist-info/WHEEL
PyDataSocket-0.0.52.dist-info/top_level.txt
PyDataSocket-0.0.52.dist-info/RECORD
