Metadata-Version: 2.1
Name: PyDataSocket
Version: 0.0.52
Summary: A Python module for sending data across TCP sockets
Home-page: https://github.com/psomers3/PyDataSocket.git
Author: Peter Somers
Author-email: psvd3@umsystem.edu
License: UNKNOWN
Platform: UNKNOWN
Classifier: Programming Language :: Python :: 3
Classifier: License :: OSI Approved :: MIT License
Classifier: Operating System :: OS Independent
Requires-Python: >=3
Requires-Dist: numpy
Requires-Dist: h5py
